README.rst
setup.py
jailconf_tools/__init__.py
jailconf_tools/parser.py
jailconf_tools.egg-info/PKG-INFO
jailconf_tools.egg-info/SOURCES.txt
jailconf_tools.egg-info/dependency_links.txt
jailconf_tools.egg-info/not-zip-safe
jailconf_tools.egg-info/top_level.txt