Metadata-Version: 1.1
Name: jailconf-tools
Version: 1.0.1
Summary: A jail.conf python library to help making administration
Home-page: https://github.com/bougie/jailconf_tools
Author: David Hymonnet
Author-email: bougie@appartland.eu
License: BSD
Keywords: freebsd jail parser
Platform: UNKNOWN
Classifier: Development Status :: 4 - Beta
Classifier: Topic :: Text Processing :: Markup
Classifier: Topic :: Terminals
Classifier: Topic :: Software Development :: Libraries
Classifier: Topic :: System :: Systems Administration
Classifier: License :: OSI Approved :: BSD License
Classifier: Programming Language :: Python :: 3
Classifier: Programming Language :: Python :: 3.3
Classifier: Programming Language :: Python :: 3.4
